kivy_sync/__init__.py
kivy_sync-0.0.0.dist-info/METADATA
kivy_sync-0.0.0.dist-info/WHEEL
kivy_sync-0.0.0.dist-info/top_level.txt
kivy_sync-0.0.0.dist-info/RECORD
