Metadata-Version: 2.4
Name: kivy-sync
Version: 0.0.0
Summary: Coming soon!
Requires-Python: >=3.6
Dynamic: requires-python
Dynamic: summary
